{
  "v1": {
    "packages": {}
  },
  "v2": {
    "packages": {
      "@elizaos/plugin-filecoin": {
        "name": "@elizaos/plugin-filecoin",
        "description": "A plugin for ElizaOS that provides creative storage solutions using Filecoin and IPFS.",
        "type": "plugin",
        "versions": {
          "1.0.0": {
            "version": "1.0.0",
            "runtimeVersion": "1.0.0-beta.27",
            "platform": "universal",
            "publishedAt": "2025-05-02T08:49:33.827Z",
            "published": false
          }
        }
      }
    }
  }
}